pytest_mimesis.py
pytest_mimesis-1.1.0.dist-info/entry_points.txt
pytest_mimesis-1.1.0.dist-info/LICENSE
pytest_mimesis-1.1.0.dist-info/WHEEL
pytest_mimesis-1.1.0.dist-info/METADATA
pytest_mimesis-1.1.0.dist-info/RECORD
